thesillyhome/model_creator/__init__.py
thesillyhome/model_creator/extract_routine.py
thesillyhome/model_creator/home.py
thesillyhome/model_creator/learning_model.py
thesillyhome/model_creator/main.py
thesillyhome/model_creator/parse_data.py
thesillyhome/model_creator/read_config_json.py
thesillyhome-0.2.8.dist-info/LICENSE
thesillyhome-0.2.8.dist-info/WHEEL
thesillyhome-0.2.8.dist-info/METADATA
thesillyhome-0.2.8.dist-info/RECORD
