Metadata-Version: 2.1
Name: thesillyhome
Version: 0.2.8
Summary: 
License: Apache 2.0
Author: Chrisopher Lai
Requires-Python: >=3.9,<4.0
Classifier: License :: Other/Proprietary License
Classifier: Programming Language :: Python :: 3
Classifier: Programming Language :: Python :: 3.10
Classifier: Programming Language :: Python :: 3.9
Requires-Dist: appdaemon (>=4.2.1,<5.0.0)
Requires-Dist: joblib (==1.1.0)
Requires-Dist: mysql-connector (==2.2.9)
Requires-Dist: tqdm (==4.64.0)
